[
  { "owner": "kodjodevf", "repo": "mangayomi", "include_prereleases": true },
  { "owner": "RyanYuuki", "repo": "AnymeX", "include_prereleases": true },
  { "owner": "pystardust", "repo": "ani-cli", "include_prereleases": true },
  { "owner": "5rahim", "repo": "seanime", "include_prereleases": true },  
  { "owner": "aniyomiorg", "repo": "aniyomi", "include_prereleases": true },
  { "owner": "komikku-app", "repo": "anikku", "include_prereleases": true },
  { "owner": "RockinChaos", "repo": "Shiru", "include_prereleases": true }
]
